couchbase_helper/__init__.py
couchbase_helper/_types.py
couchbase_helper/converters.py
couchbase_helper/exceptions.py
couchbase_helper/helper.py
couchbase_helper/n1ql.py
couchbase_helper/options.py
couchbase_helper/protocols.py
couchbase_helper/retry.py
couchbase_helper/session.py
couchbase_helper/timeout.py
couchbase_helper-0.1.2.dist-info/LICENSE
couchbase_helper-0.1.2.dist-info/METADATA
couchbase_helper-0.1.2.dist-info/WHEEL
couchbase_helper-0.1.2.dist-info/top_level.txt
couchbase_helper-0.1.2.dist-info/RECORD
