Metadata-Version: 2.2
Name: couchbase-helper
Version: 0.1.2
Summary: Simple Couchbase helper for Python 3.8+ adding basic functionality
Home-page: https://github.com/sitzz/python-couchbase-helper
Author: Thomas 'sitzz' Vang
Author-email: sitzzdk@gmail.com
License: BSD-3
Keywords: couchbase,cbase,cb,couchbase-helper
Classifier: Development Status :: 4 - Beta
Classifier: Intended Audience :: Developers
Classifier: Natural Language :: English
Classifier: License :: OSI Approved :: BSD License
Classifier: Operating System :: POSIX
Classifier: Operating System :: Microsoft :: Windows
Classifier: Operating System :: MacOS :: MacOS X
Classifier: Programming Language :: Python
Classifier: Programming Language :: Python :: 3
Classifier: Programming Language :: Python :: 3 :: Only
Classifier: Programming Language :: Python :: 3.8
Classifier: Programming Language :: Python :: 3.9
Classifier: Programming Language :: Python :: 3.10
Classifier: Programming Language :: Python :: 3.11
Classifier: Programming Language :: Python :: 3.12
Classifier: Programming Language :: Python :: 3.13
Classifier: Programming Language :: Python :: Implementation :: CPython
Classifier: Programming Language :: Python :: Implementation :: PyPy
Requires-Python: >=3.8
License-File: LICENSE
Requires-Dist: couchbase>=4.0.0
